.coveragerc
.readthedocs.yaml
CHANGELOG.md
LICENSE
MANIFEST.in
Makefile
README.md
VERSION
dev-requirements.txt
requirements.txt
setup.py
docs/Makefile
docs/conf.py
docs/configfile.rst
docs/configsessions.rst
docs/contribute.rst
docs/description.rst
docs/examples.rst
docs/generate_modules.py
docs/index.rst
docs/install.rst
docs/license.rst
docs/modules.rst
docs/quickstart.rst
docs/release-notes-0.1.0.rst
docs/release-notes-0.1.1.rst
docs/release-notes-0.2.0.rst
docs/release-notes-0.2.1.rst
docs/release-notes-0.2.2.rst
docs/release-notes-0.2.3.rst
docs/release-notes-0.2.4.rst
docs/release-notes-0.3.0.rst
docs/release-notes-0.3.1.rst
docs/release-notes-0.3.2.rst
docs/release-notes-0.3.3.rst
docs/release-notes-0.4.0.rst
docs/release-notes-0.5.0.rst
docs/release-notes-0.6.0.rst
docs/release-notes-0.6.1.rst
docs/release-notes-0.7.0.rst
docs/release-notes-0.8.0.rst
docs/release-notes-0.8.1.rst
docs/release-notes-0.8.2.rst
docs/release-notes-0.8.3.rst
docs/release-notes-0.8.4.rst
docs/release-notes-1.0.0.rst
docs/release-notes-1.0.2.rst
docs/release-notes.rst
docs/requirements.rst
docs/subinterfaces.rst
docs/support.rst
examples/get_config.py
examples/nodes.conf
examples/simple.py
examples/sysmac.py
examples/vlans_api.py
pyeapi/__init__.py
pyeapi/client.py
pyeapi/eapilib.py
pyeapi/utils.py
pyeapi.egg-info/PKG-INFO
pyeapi.egg-info/SOURCES.txt
pyeapi.egg-info/dependency_links.txt
pyeapi.egg-info/requires.txt
pyeapi.egg-info/top_level.txt
pyeapi/api/__init__.py
pyeapi/api/abstract.py
pyeapi/api/acl.py
pyeapi/api/bgp.py
pyeapi/api/interfaces.py
pyeapi/api/ipinterfaces.py
pyeapi/api/mlag.py
pyeapi/api/ntp.py
pyeapi/api/ospf.py
pyeapi/api/routemaps.py
pyeapi/api/staticroute.py
pyeapi/api/stp.py
pyeapi/api/switchports.py
pyeapi/api/system.py
pyeapi/api/users.py
pyeapi/api/varp.py
pyeapi/api/vlans.py
pyeapi/api/vrfs.py
pyeapi/api/vrrp.py
test/fixtures/dut.conf
test/fixtures/eapi.conf
test/fixtures/eapi.conf.yaml
test/fixtures/empty.conf
test/fixtures/env_path.conf
test/fixtures/ipinterfaces.json
test/fixtures/nohost.conf
test/fixtures/running_config.bgp
test/fixtures/running_config.ospf
test/fixtures/running_config.portchannel
