Metadata-Version: 2.1
Name: pyeapi
Version: 1.0.3
Summary: Python Client for eAPI
Home-page: https://github.com/arista-eosplus/pyeapi
Author: Arista EOS+ CS
Author-email: eosplus-dev@arista.com
License: BSD-3
Keywords: networking arista eos eapi
Platform: UNKNOWN
Classifier: Development Status :: 4 - Beta
Classifier: Intended Audience :: System Administrators
Classifier: Topic :: System :: Networking
Classifier: License :: OSI Approved :: BSD License
Classifier: Programming Language :: Python :: 3 :: Only
Provides-Extra: dev
Provides-Extra: test
License-File: LICENSE
